syncsketch/__init__.py
syncsketch/syncsketch.py
syncsketch-1.0.10.6.dist-info/LICENSE
syncsketch-1.0.10.6.dist-info/METADATA
syncsketch-1.0.10.6.dist-info/WHEEL
syncsketch-1.0.10.6.dist-info/top_level.txt
syncsketch-1.0.10.6.dist-info/RECORD
