Metadata-Version: 2.1
Name: syncsketch
Version: 1.0.10.6
Summary: SyncSketch Python API
Home-page: https://github.com/syncsketch/python-api
Author: Philip Floetotto
Author-email: phil@syncsketch.com
License: BSD-3-Clause
Classifier: Development Status :: 5 - Production/Stable
Classifier: Intended Audience :: Developers
Classifier: Topic :: Software Development :: Build Tools
Classifier: License :: OSI Approved :: BSD License
Classifier: Programming Language :: Python :: 2.7
Classifier: Programming Language :: Python :: 3
Classifier: Programming Language :: Python :: 3.7
Classifier: Programming Language :: Python :: 3.8
Classifier: Programming Language :: Python :: 3.9
Classifier: Programming Language :: Python :: 3.10
Classifier: Programming Language :: Python :: 3.11
Requires-Python: >=2.7, <=3.11
License-File: LICENSE
Requires-Dist: requests >=2.20.0
